unillm/__init__.py
unillm/unillm.py
unillm/version.py
unillm-0.0.8.dist-info/METADATA
unillm-0.0.8.dist-info/WHEEL
unillm-0.0.8.dist-info/entry_points.txt
unillm-0.0.8.dist-info/top_level.txt
unillm-0.0.8.dist-info/RECORD
