Metadata-Version: 2.1
Name: unillm
Version: 0.0.8
Summary: Unified Large Language Model Interface for ChatGPT, LLaMA, Mistral, Claude, and RAG
Home-page: https://github.com/fuzihaofzh/unillm
Author: Your Name
Author-email: your.email@example.com
License: MIT
Keywords: language models AI NLP ChatGPT Llama Mistral Claude MistralAI RAG
Classifier: Programming Language :: Python :: 3.8
Requires-Dist: openai
Requires-Dist: torch
Requires-Dist: transformers
Requires-Dist: PyYAML
Requires-Dist: peft
Requires-Dist: anthropic
Requires-Dist: mistralai
Requires-Dist: llama-index
Requires-Dist: fire
